zillion/__init__.py
zillion/configs.py
zillion/core.py
zillion/datasource.py
zillion/field.py
zillion/model.py
zillion/nlp.py
zillion/report.py
zillion/sql_utils.py
zillion/version.py
zillion/warehouse.py
zillion/dialects/__init__.py
zillion/dialects/conversions.py
zillion/dialects/duckdb.py
zillion/dialects/mysql.py
zillion/dialects/postgresql.py
zillion/dialects/sqlite.py
zillion/scripts/__init__.py
zillion/scripts/bootstrap_datasource_config.py
zillion/scripts/json_to_yaml.py
zillion/scripts/load_config.py
zillion/scripts/run_report.py
zillion/scripts/yaml_to_json.py
zillion-0.14.0.dist-info/licenses/AUTHORS.md
zillion-0.14.0.dist-info/licenses/LICENSE
zillion-0.14.0.dist-info/METADATA
zillion-0.14.0.dist-info/WHEEL
zillion-0.14.0.dist-info/top_level.txt
zillion-0.14.0.dist-info/RECORD
