Metadata-Version: 2.4
Name: zillion
Version: 0.14.0
Summary: Make sense of it all. Data modeling and analytics with a sprinkle of AI.
Author: totalhack
License: The MIT License (MIT)
Project-URL: Homepage, https://github.com/totalhack/zillion
Project-URL: Source, https://github.com/totalhack/zillion
Project-URL: Issues, https://github.com/totalhack/zillion/issues
Classifier: Development Status :: 3 - Alpha
Classifier: License :: OSI Approved :: MIT License
Classifier: Programming Language :: Python :: 3
Requires-Python: >=3.9
License-File: LICENSE
License-File: AUTHORS.md
Requires-Dist: climax~=0.4.0
Requires-Dist: lxml>=4.9.3
Requires-Dist: marshmallow==3.21.0; python_version >= "3.12"
Requires-Dist: marshmallow==3.20.1; python_version < "3.12"
Requires-Dist: networkx>=3.0
Requires-Dist: ordered-set~=4.1.0
Requires-Dist: pandas<3,>=2.0.0; python_version >= "3.13"
Requires-Dist: pandas<3,>=1.1; python_version < "3.13"
Requires-Dist: numpy<2,>=1.26
Requires-Dist: openpyxl<3.1.1,>=3.0.7
Requires-Dist: pymysql~=1.0.2
Requires-Dist: pyyaml>=6.0
Requires-Dist: setuptools>=65
Requires-Dist: simplejson~=3.17.0
Requires-Dist: stopit~=1.1.2
Requires-Dist: sqlalchemy<2,>=1.4.49; python_version >= "3.12"
Requires-Dist: sqlalchemy<2,>=1.3; python_version < "3.12"
Requires-Dist: sqlparse~=0.3.1
Requires-Dist: tabulate~=0.8.7
Requires-Dist: tlbx~=0.1.22
Requires-Dist: xlrd~=1.2.0
Provides-Extra: mysql
Requires-Dist: pymysql~=1.0.2; extra == "mysql"
Provides-Extra: postgres
Requires-Dist: psycopg2-binary~=2.9.5; extra == "postgres"
Provides-Extra: duckdb
Requires-Dist: duckdb==0.7.1; python_version == "3.9" and extra == "duckdb"
Requires-Dist: duckdb-engine==0.7.*; python_version == "3.9" and extra == "duckdb"
Requires-Dist: duckdb<1.0,>=0.7.1; (python_version >= "3.10" and python_version < "3.12") and extra == "duckdb"
Requires-Dist: duckdb-engine<0.10,>=0.7; (python_version >= "3.10" and python_version < "3.12") and extra == "duckdb"
Requires-Dist: duckdb>=1.0.0; python_version >= "3.12" and extra == "duckdb"
Requires-Dist: duckdb-engine<1.0,>=0.10; python_version >= "3.12" and extra == "duckdb"
Provides-Extra: nlp
Requires-Dist: langchain==0.0.115; extra == "nlp"
Requires-Dist: openai==0.27.2; extra == "nlp"
Requires-Dist: tiktoken==0.3.3; extra == "nlp"
Requires-Dist: qdrant-client==1.1.3; extra == "nlp"
Provides-Extra: dev
Requires-Dist: black; extra == "dev"
Requires-Dist: pre-commit; extra == "dev"
Requires-Dist: pylint>=3.0; extra == "dev"
Requires-Dist: pytest==7.1.2; extra == "dev"
Requires-Dist: pytest-xdist==3.1.0; extra == "dev"
Requires-Dist: twine>=5; extra == "dev"
Requires-Dist: wheel; extra == "dev"
Requires-Dist: mkdocs==1.1.2; extra == "dev"
Requires-Dist: mkdocs-material==5.2.1; extra == "dev"
Requires-Dist: mkdocs-material-extensions==1.0; extra == "dev"
Requires-Dist: mkautodoc==0.2.0; extra == "dev"
Requires-Dist: psycopg2-binary>=2.9.5; extra == "dev"
Requires-Dist: jinja2<3.1.0; extra == "dev"
Dynamic: license-file
